CHANGES
LICENSE
MANIFEST.in
README.rst
requirements.pip
setup.py
sphinxcontrib/__init__.py
sphinxcontrib/github.py
sphinxcontrib_github.egg-info/PKG-INFO
sphinxcontrib_github.egg-info/SOURCES.txt
sphinxcontrib_github.egg-info/dependency_links.txt
sphinxcontrib_github.egg-info/namespace_packages.txt
sphinxcontrib_github.egg-info/not-zip-safe
sphinxcontrib_github.egg-info/requires.txt
sphinxcontrib_github.egg-info/top_level.txt