Metadata-Version: 1.1
Name: sphinxcontrib-github
Version: 0.1.1
Summary: github directives and roles for sphinx
Home-page: https://github.com/tony/sphinxcontrib-github/
Author: Tony Narlock
Author-email: tony@git-pull.com
License: BSD
Download-URL: http://pypi.python.org/pypi/sphinxcontrib-github
Platform: UNKNOWN
Classifier: Development Status :: 3 - Alpha
Classifier: License :: OSI Approved :: BSD License
Classifier: Environment :: Console
Classifier: Environment :: Web Environment
Classifier: Intended Audience :: Developers
Classifier: Programming Language :: Python
Classifier: Operating System :: OS Independent
Classifier: Topic :: Documentation
Classifier: Topic :: Utilities
